{
  "version": "5",
  "dialect": "mysql",
  "id": "67ce4f1c-4a6b-44b6-a6c9-a335c5bf2a2e",
  "prevId": "00000000-0000-0000-0000-000000000000",
  "tables": {
    "post_tags": {
      "name": "post_tags",
      "columns": {
        "id": {
          "name": "id",
          "type": "int unsigned",
          "primaryKey": false,
          "notNull": true,
          "autoincrement": true
        },
        "posts_id": {
          "name": "posts_id",
          "type": "int unsigned",
          "primaryKey": false,
          "notNull": false,
          "autoincrement": false
        },
        "tags_id": {
          "name": "tags_id",
          "type": "int unsigned",
          "primaryKey": false,
          "notNull": false,
          "autoincrement": false
        },
        "created_at": {
          "name": "created_at",
          "type": "timestamp",
          "primaryKey": false,
          "notNull": true,
          "autoincrement": false,
          "default": "(now())"
        }
      },
      "indexes": {},
      "foreignKeys": {
        "post_tags_posts_id_posts_id_fk": {
          "name": "post_tags_posts_id_posts_id_fk",
          "tableFrom": "post_tags",
          "tableTo": "posts",
          "columnsFrom": [
            "posts_id"
          ],
          "columnsTo": [
            "id"
          ],
          "onDelete": "no action",
          "onUpdate": "no action"
        },
        "post_tags_tags_id_tags_id_fk": {
          "name": "post_tags_tags_id_tags_id_fk",
          "tableFrom": "post_tags",
          "tableTo": "tags",
          "columnsFrom": [
            "tags_id"
          ],
          "columnsTo": [
            "id"
          ],
          "onDelete": "no action",
          "onUpdate": "no action"
        }
      },
      "compositePrimaryKeys": {
        "post_tags_id": {
          "name": "post_tags_id",
          "columns": [
            "id"
          ]
        }
      },
      "uniqueConstraints": {
        "id": {
          "name": "id",
          "columns": [
            "id"
          ]
        }
      }
    },
    "posts": {
      "name": "posts",
      "columns": {
        "id": {
          "name": "id",
          "type": "int unsigned",
          "primaryKey": false,
          "notNull": true,
          "autoincrement": true
        },
        "users_id": {
          "name": "users_id",
          "type": "int unsigned",
          "primaryKey": false,
          "notNull": false,
          "autoincrement": false
        },
        "title": {
          "name": "title",
          "type": "varchar(100)",
          "primaryKey": false,
          "notNull": false,
          "autoincrement": false
        },
        "content": {
          "name": "content",
          "type": "text",
          "primaryKey": false,
          "notNull": false,
          "autoincrement": false
        },
        "posted_at": {
          "name": "posted_at",
          "type": "timestamp",
          "primaryKey": false,
          "notNull": false,
          "autoincrement": false
        },
        "posted_by": {
          "name": "posted_by",
          "type": "varchar(50)",
          "primaryKey": false,
          "notNull": false,
          "autoincrement": false
        }
      },
      "indexes": {},
      "foreignKeys": {
        "posts_users_id_users_id_fk": {
          "name": "posts_users_id_users_id_fk",
          "tableFrom": "posts",
          "tableTo": "users",
          "columnsFrom": [
            "users_id"
          ],
          "columnsTo": [
            "id"
          ],
          "onDelete": "no action",
          "onUpdate": "no action"
        }
      },
      "compositePrimaryKeys": {
        "posts_id": {
          "name": "posts_id",
          "columns": [
            "id"
          ]
        }
      },
      "uniqueConstraints": {
        "id": {
          "name": "id",
          "columns": [
            "id"
          ]
        }
      }
    },
    "tags": {
      "name": "tags",
      "columns": {
        "id": {
          "name": "id",
          "type": "int unsigned",
          "primaryKey": false,
          "notNull": true,
          "autoincrement": true
        },
        "name": {
          "name": "name",
          "type": "varchar(50)",
          "primaryKey": false,
          "notNull": false,
          "autoincrement": false
        },
        "created_at": {
          "name": "created_at",
          "type": "timestamp",
          "primaryKey": false,
          "notNull": true,
          "autoincrement": false,
          "default": "(now())"
        },
        "created_by": {
          "name": "created_by",
          "type": "varchar(50)",
          "primaryKey": false,
          "notNull": false,
          "autoincrement": false
        }
      },
      "indexes": {},
      "foreignKeys": {},
      "compositePrimaryKeys": {
        "tags_id": {
          "name": "tags_id",
          "columns": [
            "id"
          ]
        }
      },
      "uniqueConstraints": {
        "id": {
          "name": "id",
          "columns": [
            "id"
          ]
        }
      }
    },
    "users": {
      "name": "users",
      "columns": {
        "id": {
          "name": "id",
          "type": "int unsigned",
          "primaryKey": false,
          "notNull": true,
          "autoincrement": true
        },
        "name": {
          "name": "name",
          "type": "varchar(50)",
          "primaryKey": false,
          "notNull": false,
          "autoincrement": false
        },
        "email": {
          "name": "email",
          "type": "varchar(255)",
          "primaryKey": false,
          "notNull": false,
          "autoincrement": false
        },
        "password": {
          "name": "password",
          "type": "varchar(255)",
          "primaryKey": false,
          "notNull": false,
          "autoincrement": false
        },
        "created_at": {
          "name": "created_at",
          "type": "timestamp",
          "primaryKey": false,
          "notNull": true,
          "autoincrement": false,
          "default": "(now())"
        },
        "updated_at": {
          "name": "updated_at",
          "type": "timestamp",
          "primaryKey": false,
          "notNull": false,
          "autoincrement": false
        }
      },
      "indexes": {},
      "foreignKeys": {},
      "compositePrimaryKeys": {
        "users_id": {
          "name": "users_id",
          "columns": [
            "id"
          ]
        }
      },
      "uniqueConstraints": {
        "id": {
          "name": "id",
          "columns": [
            "id"
          ]
        }
      }
    }
  },
  "_meta": {
    "schemas": {},
    "tables": {},
    "columns": {}
  }
}